{
  "feature": "registry-system",
  "created": "2026-02-16T00:00:00Z",
  "updated": "2026-02-16T00:00:00Z",
  "status": "completed",
  "execution_order": [
    "types",
    "scanner",
    "metadata",
    "dependencies",
    "entry-point",
    "validation",
    "registry-core",
    "schema-export"
  ],
  "progress": {
    "total_tasks": 8,
    "completed": 8,
    "in_progress": 0,
    "pending": 0
  },
  "tasks": [
    {
      "id": "types",
      "file": "tasks/types.md",
      "title": "ModuleDescriptor, DiscoveredModule, DependencyInfo Interfaces",
      "status": "completed",
      "started_at": "2026-02-16T08:00:00Z",
      "completed_at": "2026-02-16T09:00:00Z",
      "assignee": null,
      "commits": []
    },
    {
      "id": "scanner",
      "file": "tasks/scanner.md",
      "title": "Directory Scanning with scanExtensions() and scanMultiRoot()",
      "status": "completed",
      "started_at": "2026-02-16T09:00:00Z",
      "completed_at": "2026-02-16T12:00:00Z",
      "assignee": null,
      "commits": []
    },
    {
      "id": "metadata",
      "file": "tasks/metadata.md",
      "title": "Metadata Loading, Merging, ID Map, and Dependency Parsing",
      "status": "completed",
      "started_at": "2026-02-16T12:00:00Z",
      "completed_at": "2026-02-16T14:00:00Z",
      "assignee": null,
      "commits": []
    },
    {
      "id": "dependencies",
      "file": "tasks/dependencies.md",
      "title": "Kahn's Topological Sort with Cycle Detection",
      "status": "completed",
      "started_at": "2026-02-16T14:00:00Z",
      "completed_at": "2026-02-16T17:00:00Z",
      "assignee": null,
      "commits": []
    },
    {
      "id": "entry-point",
      "file": "tasks/entry-point.md",
      "title": "Dynamic Module Loading via async import()",
      "status": "completed",
      "started_at": "2026-02-16T17:00:00Z",
      "completed_at": "2026-02-16T19:00:00Z",
      "assignee": null,
      "commits": []
    },
    {
      "id": "validation",
      "file": "tasks/validation.md",
      "title": "Module Structural Validation",
      "status": "completed",
      "started_at": "2026-02-16T19:00:00Z",
      "completed_at": "2026-02-16T20:00:00Z",
      "assignee": null,
      "commits": []
    },
    {
      "id": "registry-core",
      "file": "tasks/registry-core.md",
      "title": "Registry Class with 8-Step Discover Pipeline",
      "status": "completed",
      "started_at": "2026-02-16T20:00:00Z",
      "completed_at": "2026-02-17T01:00:00Z",
      "assignee": null,
      "commits": []
    },
    {
      "id": "schema-export",
      "file": "tasks/schema-export.md",
      "title": "Schema Query and Export Functions",
      "status": "completed",
      "started_at": "2026-02-17T01:00:00Z",
      "completed_at": "2026-02-17T04:00:00Z",
      "assignee": null,
      "commits": []
    }
  ],
  "metadata": {
    "source_doc": "planning/features/registry-system.md",
    "created_by": "code-forge",
    "version": "1.0"
  }
}
